wacy/__init__.py
wacy/apps/__init__.py
wacy/apps/base/__init__.py
wacy/apps/base/app.py
wacy/cards/__init__.py
wacy/cards/base.py
wacy/cards/dependency.py
wacy/cards/entity.py
wacy/cards/input.py
wacy/cards/similarity.py
wacy/cards/token.py
wacy/utils/__init__.py
wacy/utils/defaults.py
wacy-0.1.2.dist-info/LICENSE
wacy-0.1.2.dist-info/METADATA
wacy-0.1.2.dist-info/WHEEL
wacy-0.1.2.dist-info/top_level.txt
wacy-0.1.2.dist-info/RECORD
