Metadata-Version: 2.1
Name: wacy
Version: 0.1.2
Summary: Powering spaCy with Wave
Home-page: https://github.com/thewaverguy/wacy
Author: TheWaverGuy
Author-email: thewaverguy@gmail.com
License: Apache License, Version 2.0
Project-URL: Documentation, https://wacy.readthedocs.io
Project-URL: Source, https://github.com/thewaverguy/wacy
Project-URL: Tracker, https://github.com/thewaverguy/wacy/issues
Keywords: app,h2o_wave,nlp,spacy
Platform: any
Classifier: Programming Language :: Python :: 3.6
Classifier: Programming Language :: Python :: 3.7
Classifier: Programming Language :: Python :: 3.8
Classifier: Programming Language :: Python :: 3.9
Classifier: License :: OSI Approved :: Apache Software License
Classifier: Operating System :: OS Independent
Requires-Python: >=3.6
Requires-Dist: h2o-wave (>=0.13.0)
Requires-Dist: spacy (>=3.0.0)
